dashblock/__init__.py
dashblock/client.py
dashblock/dashblock.py
dashblock-0.0.3.dist-info/METADATA
dashblock-0.0.3.dist-info/WHEEL
dashblock-0.0.3.dist-info/top_level.txt
dashblock-0.0.3.dist-info/RECORD
