Metadata-Version: 2.1
Name: dashblock
Version: 0.0.3
Summary: Automatation SDK for python
Home-page: http://beta.dashblock.com
Author: Dashblock
Author-email: hello@dashblock.com
License: MIT
Platform: UNKNOWN
Requires-Python: >=3.6
Requires-Dist: pyee (==6.0.0)
Requires-Dist: websockets (==8.1)
